Workbook

Sheet 使い方
A1: MTG要素カタログ
A2: 自作カードゲームに取り込めそうなMTGの要素を、カードタイプからキーワード、デジタル専用メカニズム、定番のデザイン手法まで一覧にしたもの。
A4: 入力欄（薄い黄色）
A5: 採用検討：◎ 採用確定 / ○ 採用候補 / △ アレンジすれば使える / × 不採用。プルダウンから選ぶと集計シートに反映される
A6: メモ：ポイントコスト案や自分のカード名など自由記入。例）飛行 → 採用検討 ○、メモ「貫通 +2pt。ブロック値無視」
A8: 導入しやすさの基準
A9: 高：フラグや数値1つで実装できる（例：速攻、絆魂）
A10: 中：新しいゾーン・状態管理・追加UIが要る（例：墓地から唱える、カウンター管理）
A11: 低：割り込み・スタック・複雑なタイミング処理など大掛かり（例：打ち消し、瞬速の応酬）
A13: 列の見方
A14: 大分類：カードタイプ、キーワード能力、キーワード処理、能力語、デジタル専用メカニズムなど。総合ルール上の区分に準拠
A15: 機能タグ：ゲーム上の役割（攻撃、除去、ドロー・手札、墓地利用など）。デッキの役割設計やカードの並べ替えに使う
... A22: 2026年10月時点で確認できた範囲。新セットで追加された要素は今後増える

Sheet 全要素一覧
A1: No | B1: 大分類 | C1: 機能タグ | D1: 名称（日本語） | E1: 名称（英語） | F1: 総合ルール | G1: MTGでの効果 | H1: 初出 | I1: 自作ゲームへの応用案 | J1: 導入しやすさ | K1: 前提システム | L1: 採用検討 | M1: メモ
A2: 1 | B2: カードタイプ | C2: ルール基盤 | D2: アーティファクト | E2: Artifact | F2: 301 | G2: 無色のものが多い人工物のパーマネント。色を問わず採用でき、装備品や機体などのサブタイプで役割が広がる。 | H2: アルファ (1993) | I2: どのデッキにも入る無属性の装置カード枠として実装する。属性制限を外す代わりにポイント単価を属性カードより高めに設定すると、汎用性と強さの釣り合いが取れる。 | J2: 高 | K2: 永続カード枠 | L2: × | M2: 色が無いので全カードが既に無色。既存：全カード
A3: 2 | B3: カードタイプ | C3: 攻撃 | D3: バトル | E3: Battle | F3: 310 | G3: 守備カウンターで耐久を表すパーマネント。対戦相手が守る側となり、攻撃して守備値を0にすると多くは裏面に変身して報酬になる。 | H3: 機械兵団の進軍 (2023) | I3: 相手側に攻略目標を置くカード。耐久を削り切ると裏面の強力な効果が手に入る形にすると、攻撃を本体と目標のどちらに振るかの判断が生まれる。耐久と報酬からポイントを逆算する。 | J3: 中 | K3: 耐久値・攻撃先選択 | L3: △ | M3: 相手の場に攻撃しない『砦』モンスターを置き、倒すと相手が報酬を得る形なら可。裏面・変身は重い
A4: 3 | B4: カードタイプ | C4: 攻撃 | D4: クリーチャー | E4: Creature | F4: 302 | G4: パワーとタフネスを持ち、攻撃とブロックを担う主力のパーマネント。出たターンは召喚酔いで攻撃できない。 | H4: アルファ (1993) | I4: 場に残って毎ターン働く召喚ユニット。攻撃値と耐久値をポイント1点あたりの換算表で決めると予算管理しやすい。StS型の本体戦闘と並立させるなら、ユニットは自動攻撃にすると操作が軽い。 | J4: 中 | K4: 盤面・ユニット管理 | L4: × | M4: 既存：モンスター
A5: 4 | B5: カードタイプ | C5: 強化 | D5: エンチャント | E5: Enchantment | F5: 303 | G5: 場に残り続けて継続的な効果を与える魔法のパーマネント。オーラや英雄譚など多様なサブタイプを持つ。 | H5: アルファ (1993) | I5: StSのパワーカードに相当する永続効果枠。一度使えば戦闘中ずっと効果が続く。効果量×想定持続ターン数でポイントを見積もり、除去手段の有無で補正する。 | J5: 高 | K5: 永続効果枠 | L5: × | M5: 既存：パワー
A6: 5 | B6: カードタイプ | C6: 妨害 | D6: インスタント | E6: Instant | F6: 304 | G6: 優先権があればいつでも唱えられる使い切りの呪文。相手の行動への対応や戦闘中の奇襲に使う。 | H6: アルファ (1993) | I6: 相手ターン中に使える割り込みカード。オンラインでは制限時間付きの応答待ちが要る。初期実装は「相手の攻撃時に自動で発動する罠」として予約型にすると処理が軽い。 | J6: 低 | K6: 割り込みタイミング | L6: △ | M6: 割り込み不可。予約型の『罠』（相手が攻撃したら発動）なら既存：反撃の拡張として可
A7: 6 | B7: カードタイプ | C7: デッキ構築 | D7: 同族 | E7: Kindred | F7: 308 | G7: 他のカード・タイプと組み合わさり、そのカードにクリーチャー・タイプを持たせるカード・タイプ。旧称は部族で2024年に改名。 | H7: 未来予知 (2007) | I7: スキルや装置カードに種族タグを付ける仕組み。ドラゴン・タグ付きのスキルがドラゴン強化の恩恵を受けるようにすれば種族デッキの幅が広がる。タグ付与自体に少額のポイントを課す。 | J7: 高 | K7: タグ・種族システム | L7: △ | M7: 種族タグをスキルにも付ける案。No.53の種族タグに統合して検討
A8: 7 | B8: カードタイプ | C8: コスト・リソース | D8: 土地 | E8: Land | F8: 305 | G8: マナを生む基盤のパーマネント。唱えずにプレイし、原則1ターンに1枚まで戦場に出せる。 | H8: アルファ (1993) | I8: エネルギー上限を恒久的に伸ばす資源カードとして移植できる。1ターン1枚の制限を付け、資源と通常カードの比率をデッキ構築の要素にする。資源事故対策にドローと選べる2択カードも用意する。 | J8: 中 | K8: マナ/エネルギー | L8: × | M8: 土地・マナ前提。エナジーは自動成長で既存
A9: 8 | B9: カードタイプ | C9: 反復・再利用 | D9: プレインズウォーカー | E9: Planeswalker | F9: 306 | G9: 忠誠カウンターを増減させて1ターンに1回能力を使う味方の魔法使い。攻撃されると忠誠度を失う。 | H9: ローウィン (2007) | I9: 場に置くサブ司令塔カード。耐久値と能力の使用リソースを兼ね、毎ターン能力を1つ選んで使う。相手は本体とこのカードのどちらを狙うか選べる。能力数と初期値でポイントを算出する。 | J9: 中 | K9: 盤面・攻撃先選択 | L9: △ | M9: 重い。パワーに『ターン開始時』効果を持たせる既存の形で代用可
A10: 9 | B10: カードタイプ | C10: ルール基盤 | D10: ソーサリー | E10: Sorcery | F10: 307 | G10: 自分のメイン・フェイズでスタックが空のときだけ唱えられる使い切りの呪文。インスタントより強い効果を持ちやすい。 | H10: アルファ (1993) | I10: StSの通常のアタック・スキルカードがこれに当たる。自ターン専用である代わりに、割り込み可能なカードより同じポイントで効果量を1〜2割増やすとタイミングの価値差を表現できる。 | J10: 高 | K10: なし | L10: × | M10: 既存：全カードが自ターン専用
A11: 10 | B11: カードタイプ | C11: 反復・再利用 | D11: ダンジョン | E11: Dungeon | F11: 309 | G11: ゲームの外から統率領域に置き、探索するたび部屋を1つ進んで部屋能力を得る定形外カード。最奥に着くと踏破となる。 | H11: フォーゴトン・レルム探訪 (2021) | I11: 分岐ルート付きの進行ボードを盤面外に用意し、特定カードで1マス進むたび報酬を得る。踏破回数を参照するカードも作れる。各マスの報酬価値を合算して進行効果のポイントを決める。 | J11: 中 | K11: 進行トラック・UI | L11: × | M11: 進行ボードのUIが重く、面白さに対して実装過大
A12: 11 | B12: カードタイプ | C12: 多人数・交流 | D12: 次元 | E12: Plane | F12: 311 | G12: プレインチェイス戦で使う大判カード。全員に影響する環境効果を持ち、次元ダイスの出目で別の次元へ移る。 | H12: プレインチェイス (2009) | I12: 対戦ごとに無作為に決まるフィールド効果として導入する。全員共通のルール変化をダイスで切り替えれば、オンライン対戦の展開が毎回変わる。カードのポイントには含めない環境枠として扱う。 | J12: 中 | K12: 共有フィールド枠 | L12: △ | M12: 対戦ごとのランダムなフィールド効果（オプション）なら可。カード要素ではない
A13: 12 | B13: カードタイプ | C13: 多人数・交流 | D13: 現象 | E13: Phenomenon | F13: 312 | G13: 次元デッキに混ざる一度きりのイベント・カード。公開されると全体に作用する効果を起こし、すぐ次へ移る。 | H13: プレインチェイス2012 (2012) | I13: フィールド効果の山に混ぜる突発イベント。めくれた瞬間に全員へ1回だけ作用する（全員1枚引くなど）。デジタルなので演出付きで出せ、対戦のマンネリ防止に役立つ。 | J13: 中 | K13: 共有フィールド枠 | L13: × | M13: 共有の次元デッキ・多人数前提
... A25: 24 | B25: サブタイプ | C25: 成長・カウンター | D25: 宇宙船 | E25: Spacecraft | F25: 721 | G25: 配備で他のクリーチャーのパワー分の蓄積カウンターを溜め、規定数を超えると飛行を持つクリーチャーなどになるアーティファクト。 | H25: 久遠の終端 (2025) | I25: 他ユニットの攻撃力を燃料として注ぎ込み、閾値ごとに能力が開放される成長型カード。進捗バーで可視化でき、段階数と最終形の強さでポイントを配分する。 | J25: 中 | K25: カウンター・閾値 | L25: × | M25: 蓄積カウンター＋他ユニットのタップ前提で重い
A26: 25 | B26: サブタイプ | C26: 反復・再利用 | D26: からくり | E26: Contraption | G26: アン・セット専用。別デッキから組み立てて3つの起動輪に置き、毎ターン回る発動！カウンターと一致した輪のものを発動する。 | H26: Unstable (2017) | I26: 本デッキとは別の小デッキから出る装置を3レーンに置き、ターンごとに順番にレーンが起動する仕組み。周期的な効果の可視化はデジタル向き。起動周期を考え、効果量の3分の1程度で評価する。 | J26: 中 | K26: 別デッキ・レーン管理 | L26: × | M26: アン・セット専用・別デッキ前提
A27: 26 | B27: サブタイプ | C27: その他 | D27: アトラクション | E27: Attraction | F27: 717 | G27: 専用のアトラクション・デッキから開いて戦場に出し、毎ターンのダイスの出目が点灯している数字と一致すると効果が出る。 | H27: Unfinity (2022) | I27: 別デッキから出る施設カードに当たり目を設定し、毎ターン自動ダイスで当たれば発動する。当たり目の数で期待値が決まるので、ポイントは効果量×当たり確率で計算できる。 | J27: 中 | K27: 別デッキ・乱数 | L27: × | M27: 別デッキ・ダイス前提
A28: 27 | B28: サブタイプ | C28: ドロー・手札 | D28: 本 | E28: Book | F28: 205.3g | G28: ストリクスヘイヴンの秘密で新設されたアーティファクト・タイプ。固有ルールはなく、ドロー能力を持つものが多い。 | H28: ストリクスヘイヴンの秘密 (2026) | I28: ドロー系の装置に付けるタグ。本の枚数を数えるカードと組めばテーマデッキの軸になる。タグ自体は無料とし、参照する側のカードにポイントを持たせる。 | J28: 高 | K28: タグシステム | L28: × | M28: 効果の無いタグのみ
A29: 28 | B29: サブタイプ | C29: 条件ボーナス | D29: ボブルヘッド | E29: Bobblehead | F29: 205.3g | G29: Fallout統率者デッキで登場したアーティファクト・タイプ。主にマナを出し、ボブルヘッドの数を数えるカードで強くなる。 | H29: Fallout (2024) | I29: 小型の収集品カードを集めるほど効果が伸びるコレクション系タグ。1枚では弱く、所持数を参照するカードで化ける。数を数える効果のポイント係数を別に定めておく。 | J29: 高 | K29: タグシステム | L29: × | M29: マナ・タグ前提
A30: 29 | B30: サブタイプ | C30: 条件ボーナス | D30: インフィニティ | E30: Infinity | F30: 205.3g | G30: インフィニティ・ストーンを表すアーティファクト・タイプ。伝説の破壊不能な装置で、装着すると強力な∞能力が働く。 | H30: マーベル スパイダーマン (2025) | I30: 一定の手順で装着すると隠し能力が開放される特別枠のカード。最高レアリティ専用の演出として使い、開放前後の効果を別々にポイント化する。 | J30: 中 | K30: 状態フラグ | L30: × | M30: 装着手順の特殊枠。重い
A31: 30 | B31: サブタイプ | C31: 強化 | D31: オーラ | E31: Aura | F31: 303.4 | G31: パーマネントやプレイヤーにつけて効果を与えるエンチャント。つけ先がなくなると墓地へ置かれる。 | H31: アルファ (1993) | I31: 敵味方どちらにも貼れる付与カード。味方の強化にも相手の弱体化にも使える。つけ先が倒れると一緒に消えるリスクがあるため、装備型よりポイントを安くする。 | J31: 中 | K31: 装着管理 | L31: × | M31: 既存：攻撃力アップ／弱化／守備力アップ（永続付与）
A32: 31 | B32: サブタイプ | C32: 妨害 | D32: 呪い | E32: Curse | F32: 205.3h | G32: プレイヤーにつけるオーラのサブタイプ。対戦相手に貼り付いて継続的な不利益を与える。 | H32: イニストラード (2011) | I32: ユーザーのゲームの呪いカードと相性が良い。山札に混ぜる呪いとは別に、相手本体に貼り付いて毎ターン不利益を与える呪縛タイプを作り、解除手段もセットで用意する。 | J32: 高 | K32: 状態異常枠 | L32: ◎ | M32: 【今回実装：呪縛】今回実装 効果『呪縛』doom：相手に減らない継続ダメージ（相手のターン開始時。浄化で消える）
A33: 32 | B33: サブタイプ | C33: デッキ構築 | D33: 背景 | E33: Background | F33: 205.3h | G33: 伝説のエンチャントのサブタイプ。背景選択を持つ統率者と組んで2枚目の統率者になり、統率者を強化する。 | H33: 統率者レジェンズ：バルダーズ・ゲートの戦い (2022) | I33: リーダーカードと組み合わせる出自カード。リーダーと出自の2枚選択制にすると組み合わせで戦い方が変わる。出自は控えめな常時効果に限定し、ポイント上限を設ける。 | J33: 高 | K33: キャラ選択 | L33: × | M33: 統率者前提
A34: 33 | B34: サブタイプ | C34: 条件ボーナス | D34: 祭殿 | E34: Shrine | F34: 205.3h | G34: 祭殿の数を参照して効果が大きくなるエンチャント。神河物語で登場し、後に伝説の祭殿サイクルが作られた。 | H34: 神河物語 (2004) | I34: 同じタグのカードを並べるほど1枚ごとの効果が伸びる仕組み。3枚並ぶと効果が数倍になるため、1枚目単体は弱く設定してポイントを抑える。 | J34: 高 | K34: タグ参照 | L34: ◎ | M34: 【今回実装：自分のパワーが2つ以上】今回実装 条件『自分のパワーが2つ以上』twoPowers
A35: 34 | B35: サブタイプ | C35: 強化 | D35: カルトーシュ | E35: Cartouche | F35: 205.3h | G35: アモンケットのオーラのサブタイプ。自分のクリーチャーにつけて強化し、試練などカルトーシュを参照する能力を誘発させる。 | H35: アモンケット (2017) | I35: 付与カードを貼るたびに別のカードが誘発する連鎖の起点となるタグ。カルトーシュ型の付与で手札に戻る報酬を用意すると、付与を軸にしたデッキが組める。 | J35: 高 | K35: 装着・誘発 | L35: × | M35: オーラ・タグ誘発前提
A36: 35 | B36: サブタイプ | C36: 強化 | D36: ルーン | E36: Rune | F36: 205.3h | G36: カルドハイムのオーラのサブタイプ。パーマネントにつき、出たときにカードを1枚引く。装備品につけると装備先に能力を与える。 | H36: カルドハイム (2021) | I36: ユニットにも装備にも貼れる付与で、貼った時点で1枚引ける。損をしにくいのでポイント単価は通常の付与よりやや高めにする。 | J36: 高 | K36: 装着管理 | L36: × | M36: 既存：攻撃力アップ＋ドローの組み合わせで作れる
A37: 36 | B37: サブタイプ | C37: 成長・カウンター | D37: プラン | E37: Plan | F37: 205.3h | G37: 条件を満たすたびにプラン・カウンターが置かれ、規定数に達すると生け贄に捧げて大きな効果を起こすエンチャント。 | H37: マーベル スーパー・ヒーローズ (2026) | I37: 悪役の陰謀カード。条件達成でゲージが溜まり、満タンで強力な効果が発動する。相手から見えるゲージが阻止の駆け引きを生む。段階数と最終効果でポイントを算出する。 | J37: 高 | K37: カウンター・閾値 | L37: △ | M37: ゲージ付きパワー。#154 蓄積カウンターと同じ仕組みで後で
A38: 37 | B38: サブタイプ | C38: コスト・リソース | D38: 基本土地タイプ（平地・島・沼・山・森） | E38: Basic land types | F38: 305.6 | G38: 平地・島・沼・山・森の5種。対応する色のマナを出す能力を自動で持ち、土地渡りなど多くのカードが参照する。 | H38: アルファ (1993) | I38: 5属性に対応する資源タイプにする。各属性の資源から対応する属性のエネルギーが出る形にすれば、多色デッキの資源配分が構築の悩みどころになる。 | J38: 中 | K38: 色・属性システム | L38: × | M38: 色・土地前提
... A50: 49 | B50: サブタイプ | C50: ドロー・手札 | D50: 講義 | E50: Lesson | F50: 205.3k | G50: ストリクスヘイヴンの呪文タイプ。履修などでサイドボードから講義カードを手札に加えられる。 | H50: ストリクスヘイヴン：魔法学院 (2021) | I50: デッキ外の控えカードから状況に応じて1枚を手札に呼び込む。控え枠を5枚程度に固定し、呼び込む効果にポイントを割り当てると構築の幅が広がる。 | J50: 中 | K50: サイドボード枠 | L50: × | M50: サイドボード前提
A51: 50 | B51: サブタイプ | C51: その他 | D51: 合唱 | E51: Chorus | G51: MTGアリーナ限定の呪文タイプ。総合ルールにはなく、合唱を参照するデジタル専用カードと組む。 | H51: アルケミー：イクサラン (2023) | I51: デジタル専用カードの分類タグの例。紙では難しい効果（無作為生成や恒久強化）を持つカードを1つのタグにまとめ、そのタグを数えるカードで統一感を出す。 | J51: 高 | K51: タグシステム | L51: × | M51: デジタル分類タグのみ
A52: 51 | B52: サブタイプ | C52: 攻撃 | D52: 包囲戦 | E52: Siege | F52: 205.3q | G52: バトル・タイプ。対戦相手を守る者に選んで戦場に出し、守備カウンターを全て取り除くと追放して変身面を無料で唱えられる。 | H52: 機械兵団の進軍 (2023) | I52: 相手側に置く攻略目標で、撃破すると裏面の強力なユニットや効果が手に入る。撃破に必要なダメージと報酬の大きさから逆算してポイントを決める。 | J52: 中 | K52: 攻撃先選択 | L52: △ | M52: No.2と同じ。相手側の攻略目標は新ゾーンが要る
A53: 52 | B53: サブタイプ | C53: デッキ構築 | D53: プレインズウォーカー・タイプ | E53: Planeswalker types | F53: 205.3j | G53: ジェイスやチャンドラなど人物名がサブタイプになる。かつては同タイプのPWを1体しか持てないルールがあった。 | H53: ローウィン (2007) | I53: 人物名をタグにして同じ人物のカードを参照させる。同じ人物は場に1枚までとすれば、人物の差し替えによる立て直しが戦略になる。 | J53: 高 | K53: タグシステム | L53: × | M53: 人物タグ前提
A54: 53 | B54: サブタイプ | C54: デッキ構築 | D54: クリーチャー・タイプ（部族シナジー） | E54: Creature types | F54: 205.3m | G54: エルフやゴブリンなど種族・職業を表す300種以上のサブタイプ。同タイプを強化するロードや部族カードがデッキの軸になる。 | H54: アルファ (1993) | I54: 種族タグを5〜8種に絞り、各種族に「同種族1体ごとに強化」や「同種族をサーチ」を配る。種族数が多すぎると構築が分散するので、最初は少数で始め拡張時に追加する。 | J54: 高 | K54: タグシステム | L54: ◎ | M54: 【今回実装：種族タグ＋条件『同じ種族の自分のモンスターがいる』・修飾『同じ種族1体につき』・対象『同じ種族の自分のモンスター全体』（`tribe`・バッチC2）】（審査時は○）種族タグ（5〜8種）＋条件『同種族が2体以上』・効果『同種族1体ごとに攻撃力+N』。タグ機構が要る
A55: 54 | B55: カードレイアウト | C55: その他 | D55: 分割カード | E55: Split card | F55: 709 | G55: 1枚に小さな呪文2つを並べ、唱える時にどちらか一方を選ぶ。手札や墓地では両半分の特性を併せ持つものとして扱う。 | H55: インベイジョン (2000) | I55: 1枚に軽い効果Aと重い効果Bを載せ、使う時にどちらかを選ぶ。ポイントは両方の合計より割安にし、状況対応力そのものに値段を付ける。UIは左右タップで選択。 | J55: 高 | K55: なし | L55: ◎ | M55: 【今回実装：モード選択（次のうち1つを選ぶ）（`modes`・バッチC2）】（審査時は○）選択式カード：効果A/Bを使用時に選ぶ。ポイントは高い方＋低い方の3割
A56: 55 | B56: カードレイアウト | C56: コスト・リソース | D56: 部屋 | E56: Room | F56: 709 | G56: 2つの扉を持つ分割エンチャント。片方の扉だけ開けた状態で出し、後からコストを払って残りの扉を開けると追加の効果が働く。 | H56: ダスクモーン：戦慄の館 (2024) | I56: 設置型カードに第2の扉を用意し、後でエネルギーを払って開けると別効果が起動する。1枚が中長期の投資先になり、ポイントは扉ごとに個別に計上できる。 | J56: 中 | K56: 場に残るカード | L56: × | M56: 扉の開閉が重い。パワーで代用可
A57: 56 | B57: カードレイアウト | C57: 条件ボーナス | D57: 反転カード | E57: Flip card | F57: 710 | G57: 上下逆さにもう一つの特性を印刷し、条件を満たすと戦場のパーマネントを反転させて強化版に切り替える。元には戻らない。 | H57: 神河物語 (2004) | I57: 条件達成で上位形態に変わる一方通行の進化カード。デジタルなら演出付きで切り替えを見せられ、条件の難しさに応じて変化後ステータスのポイントを割り引ける。 | J57: 中 | K57: 場に残るカード | L57: △ | M57: 条件達成でモンスターが強化版に変わる『進化』。変身データが要る
A58: 57 | B58: カードレイアウト | C58: 条件ボーナス | D58: 変身する両面カード | E58: Transforming double-faced card | F58: 712 | G58: 表裏の両面に別々の特性を持ち、効果によって裏返る。人狼のように条件次第で何度も表裏を行き来するものもある。 | H58: イニストラード (2011) | I58: 表裏で別性能のカードを作り、条件で何度でも切り替え可能にする。裏面を常時プレビューできるUIで情報差を減らす。状態を持つぶんポイント上限を高めに設定する。 | J58: 中 | K58: 状態フラグ | L58: △ | M58: No.56と統合。何度も表裏は不要
A59: 58 | B59: カードレイアウト | C59: コスト・リソース | D59: モードを持つ両面カード | E59: Modal double-faced card (MDFC) | F59: 712 | G59: 手札から出すときにどちらの面としてプレイするかを選ぶ両面カード。片面が土地のものが多く、マナ事故の緩和に役立つ。 | H59: ゼンディカーの夜明け (2020) | I59: 表は攻撃カード、裏はエネルギー供給カードのように、使うときに面を選べる。手札事故を減らす救済枠として、片面ずつのポイントをやや低めに設定する。 | J59: 高 | K59: なし | L59: × | M59: No.54の選択式カードで十分
A60: 59 | B60: カードレイアウト | C60: 強化 | D60: 合体 | E60: Meld | F60: 701.42 | G60: 対になる特定の2枚を両方コントロールし条件を満たすと、2枚が1体の巨大なパーマネントに合わさる。 | H60: 異界月 (2016) | I60: 対になる2枚を場に揃え条件を満たすと合体ユニットに変わる。デッキに組み込む難度が高いぶん、合体後のポイントを2枚分以上にしてロマン枠にする。 | J60: 中 | K60: 場に残るカード | L60: × | M60: 2枚合体は重くロマン枠
A61: 60 | B61: カードレイアウト | C61: 反復・再利用 | D61: 出来事 | E61: Adventure | F61: 715 | G61: クリーチャーに小さな呪文が付属し、先に呪文として使うと追放され、後でその追放領域からクリーチャー本体を唱えられる。 | H61: エルドレインの王権 (2019) | I61: 1枚に先に使う小技と後で出す本体を持たせ、小技使用後は専用の待機ゾーンへ置く。1枚で2回行動できるため、ポイントは単体カードより割高に設定する。 | J61: 中 | K61: 待機ゾーン | L61: △ | M61: 小技を使った後に本体を出す待機ゾーンが要る。後回し
A62: 61 | B62: カードレイアウト | C62: 山札操作 | D62: 前兆 | E62: Omen | F62: 720 | G62: クリーチャーに付属する前兆呪文として唱えると、解決後に墓地でなくライブラリーに切り直される。後で本体として引き直せる。 | H62: タルキール：龍嵐録 (2025) | I62: 呪文面で使うと捨て札ではなく山札にシャッフルされる。リソースが山札に戻るので長期戦向け。StS型の山札循環と相性がよく、前兆面のポイントを安くできる。 | J62: 高 | K62: 山札シャッフル | L62: ◎ | M62: 【今回実装：カードの能力『循環』（`shuffleBack`・バッチB）】（審査時は○）修飾『循環』：使った後に捨て札でなく山札に混ぜる。+1pt 程度
A63: 62 | B63: カードレイアウト | C63: 反復・再利用 | D63: 英雄譚 | E63: Saga | F63: 714 | G63: 毎ターン伝承カウンターが増え、章ごとに異なる効果が順番に起動し、最終章の後に生け贄に捧げられるエンチャント。 | H63: ドミナリア (2018) | I63: 設置すると毎ターン章が進み、決まった順に効果が出る時限カード。数ターン先の予定表になるため、CPU敵の行動予告の表示形式にも転用できる。 | J63: 高 | K63: ターン開始処理 | L63: ◎ | M63: 【今回実装：英雄譚（章つきのパワー）（`saga`・バッチC2）】（審査時は○）章付きパワー：条件『設置からNターン目』で効果が順に出て最後に消える。パワーの経過ターン管理が要る
... A67: 66 | B67: カードレイアウト | C67: 反復・再利用 | D67: 準備 | E67: Preparation card (prepare spell) | F67: 722 | G67: クリーチャーに準備・呪文が付属し、準備済状態の間はその呪文のコピーを追放領域から1回唱えられる。唱えると未準備状態になる。 | H67: ストリクスヘイヴンの秘密 (2026) | I67: ユニットが場にいる間だけ使える付属スキルをカード化する。使うと未準備になり、再準備効果で再利用できる。使用回数の管理はデジタルなら容易。 | J67: 中 | K67: 状態フラグ | L67: × | M67: 追放からの再使用・状態フラグが重い
A68: 67 | B68: カードレイアウト | C68: 強化 | D68: 宿主・増強（非公式訳） | E68: Host / Augment | G68: 上半分だけの増強カードを宿主クリーチャーの上に重ねると、2枚の名前と能力が合わさって1体のクリーチャーになる。Un-セットの仕組み。 | H68: Unstable (2017) | I68: 半分だけのパーツカードを既存ユニットに装着し、名前と能力を合成する。組み合わせごとに新しいカードが生まれ、ポイント合算方式と非常に相性がよい。 | J68: 中 | K68: 場に残るカード | L68: × | M68: 名前・能力の合成は重い
A69: 68 | B69: ゾーン | C69: ルール基盤 | D69: ライブラリー | E69: Library | F69: 401 | G69: プレイヤーの山札。裏向きで順番は非公開。ここからカードを引き、空のときに引こうとすると敗北する。 | H69: アルファ (1993) | I69: StSの山札と同じ。MTGでは山札が尽きると負けるが、対戦ゲームなら「山札切れで疲労ダメージ」など緩い罰則に置き換えると遅延戦術を抑えられる。 | J69: 高 | K69: なし | L69: × | M69: 既存：山札（切れたら捨て札を切り直す）。山札切れ敗北は不要
A70: 69 | B70: ゾーン | C70: ドロー・手札 | D70: 手札 | E70: Hand | F70: 402 | G70: 引いたカードを持つ非公開の領域。クリンナップ・ステップで上限の7枚を超えた分を捨てる。 | H70: アルファ (1993) | I70: StSと違いターン終了で手札を捨てず持ち越す方式も選べる。持ち越し型は長期計画、全捨て型はテンポ重視になる。カード単位で「保留」能力として選ばせる中間案もある。 | J70: 高 | K70: なし | L70: × | M70: 既存：手札（毎ターン全捨て＋保持）
A71: 70 | B71: ゾーン | C71: ルール基盤 | D71: 戦場 | E71: Battlefield | F71: 403 | G71: パーマネントが置かれる共有の公開領域。土地やクリーチャー、アーティファクトなどが存在し続ける。 | H71: アルファ (1993) | I71: StSでは薄い「場に残るカード」の領域。ユニットや装置を置く盤面を作ると、一時効果と永続カードで戦略が分かれる。枠数に上限を設けると画面設計も楽になる。 | J71: 中 | K71: 盤面UI | L71: × | M71: 既存：モンスターの場・パワー枠
A72: 71 | B72: ゾーン | C72: 墓地利用 | D72: 墓地 | E72: Graveyard | F72: 404 | G72: 使った呪文や死んだクリーチャー、捨てたカードが置かれる公開領域。順番を保ち、再利用の対象になる。 | H72: アルファ (1993) | I72: StSの捨て札に当たるが、MTGでは山札に戻らず再利用の資源になる。捨て札から回収する効果や枚数を参照する効果を作るなら、一部のカードは捨て札に留まる設計を入れる。 | J72: 高 | K72: 捨て札ゾーン | L72: × | M72: 既存：捨て札。活用は条件側（#532スレッショルド・#533宿根）で行う
A73: 72 | B73: ゾーン | C73: ルール基盤 | D73: スタック | E73: Stack | F73: 405 | G73: 唱えた呪文や誘発した能力が解決を待つ領域。最後に置かれたものから順に解決される。 | H73: 第6版 (1999) | I73: 相手が対応してカードを重ねる割り込み合戦の基盤。オンラインでは通信待ちが増えるため、対応できるカードを限定し、応答は1回までの簡易スタックにするのが現実的。 | J73: 低 | K73: 割り込みタイミング | L73: × | M73: スタック・割り込みはこのゲームに無い
A74: 73 | B74: ゾーン | C74: 除去 | D74: 追放 | E74: Exile | F74: 406 | G74: ゲームから取り除かれたカードの領域。原則戻らないが、一時的に追放して後で使う効果も多い。 | H74: アルファ (1993) | I74: StSの廃棄に当たる。強力な使い切りカードは廃棄送りにしてポイントを割り引く。一部のカードで廃棄から帰還させると、廃棄も資源になる。 | J74: 高 | K74: 廃棄ゾーン | L74: ◎ | M74: 【今回実装：廃棄】今回実装 デメリット『廃棄』exhaust：使ったあと捨て札でなく除外（呪文のみ）
A75: 74 | B75: ゾーン | C75: ルール基盤 | D75: 統率領域 | E75: Command zone | F75: 408 | G75: 統率者や紋章、次元、計略などを置く特殊な領域。ここにあるものはゲーム全体に作用し続ける。 | H75: プレインチェイス (2009) | I75: 盤面外の常設枠。リーダーカード、獲得した恒久バフ、フィールド効果をまとめて表示する領域として設計すれば、除去されない効果の置き場になる。 | J75: 中 | K75: 常設UI枠 | L75: × | M75: 統率領域・常設枠は前提が無い
A76: 75 | B76: ゾーン | C76: 多人数・交流 | D76: アンティ | E76: Ante | F76: 407 | G76: 開始時に各自のデッキから1枚を賭け、勝者が所有権を得る初期のルールと領域。現在は公式に禁止されている。 | H76: アルファ (1993) | I76: 実カードの賭けは避けるべきだが、勝利報酬として「相手デッキのカード1枚の複製を獲得」は可能。賭博と誤解されないよう、所有権や課金通貨は動かさない方が安全。 | J76: 中 | K76: アカウント・報酬 | L76: × | M76: 賭け・所有権の移動は不採用
A77: 76 | B77: ゾーン | C77: デッキ構築 | D77: サイドボード（ゲームの外部） | E77: Sideboard | F77: 100.4 | G77: デッキとは別に持つ控えのカード。試合間の入れ替えや、ゲーム外からカードを持ち込む効果に使う。 | I77: 試合間にメインと入れ替えられる控え枠。3本勝負で相手に合わせた調整ができる。控えの枚数上限と、控えからカードを呼ぶ効果のポイント単価を決めておく。 | J77: 中 | K77: BO3・デッキ編集 | L77: × | M77: BO3・サイドボードの仕組みが無い
A78: 77 | B78: ターン構造 | C78: ルール基盤 | D78: ターン（フェイズとステップ） | E78: Turn structure | F78: 500 | G78: ターンは開始・戦闘前メイン・戦闘・戦闘後メイン・終了の5フェイズからなり、一部はさらにステップに分かれる。 | H78: アルファ (1993) | I78: 誘発タイミングの基準点を決める設計図として流用する。まずはターン開始時・行動フェイズ・ターン終了時の3点に絞ると、カード効果の記述とCPUの処理が単純になる。 | J78: 高 | K78: なし | L78: × | M78: 既存：ターン開始・行動・ターン終了のタイミング
A79: 78 | B79: ターン構造 | C79: ルール基盤 | D79: アンタップ・ステップ | E79: Untap step | F79: 502 | G79: ターン開始直後に、アクティブ・プレイヤーのパーマネントをすべてアンタップする。誰も呪文を唱えられない。 | H79: アルファ (1993) | I79: 毎ターンの行動権リセット。使用済みのカードを再び使えるようにする処理として実装し、リセットを1回飛ばす凍結デバフを作る余地を残す。 | J79: 高 | K79: 使用済み状態 | L79: × | M79: 既存：攻撃権の毎ターン回復＋凍結
A80: 79 | B80: ターン構造 | C80: 反復・再利用 | D80: アップキープ・ステップ | E80: Upkeep step | F80: 503 | G80: ターン開始時の誘発を処理するステップ。維持コストや毎ターン起きる効果がここで誘発する。 | H80: アルファ (1993) | I80: ターン開始時効果の標準タイミング。毎ターンの維持費を要求するカードも作れる。維持費は長期的な負担なので、本体のポイントを割り引く根拠になる。 | J80: 高 | K80: ターン開始処理 | L80: × | M80: 既存：ターン開始時のタイミング／デメリット『維持費』
A81: 80 | B81: ターン構造 | C81: ドロー・手札 | D81: ドロー・ステップ | E81: Draw step | F81: 504 | G81: カードを1枚引くステップ。2人対戦の先攻プレイヤーは最初のターンに引かない。 | H81: アルファ (1993) | I81: 毎ターンの基本ドロー。StS型の毎ターン引き直しと違い1枚ずつ増える方式にすると手札管理型になる。先攻有利の補正として後攻に追加ドローやエネルギーを与えるのが定番。 | J81: 高 | K81: なし | L81: × | M81: 既存：毎ターン5枚ドロー
A82: 81 | B82: ターン構造 | C82: ルール基盤 | D82: 戦闘前メイン・フェイズ | E82: Precombat main phase | F82: 505 | G82: ターン最初のメイン・フェイズ。土地をプレイし、ソーサリー・タイミングの呪文や能力を使える。 | H82: アルファ (1993) | I82: プレイヤーが主に行動するフェイズ。戦闘を挟む2回メイン制にすると「攻撃前に強化するか、結果を見てから出すか」の選択が生まれる。 | J82: 高 | K82: なし | L82: × | M82: フェイズ分割なし。カードと攻撃は自由な順で行える
A83: 82 | B83: ターン構造 | C83: 妨害 | D83: 戦闘開始ステップ | E83: Beginning of combat step | F83: 507 | G83: 戦闘フェイズ最初のステップ。攻撃の宣言前に呪文を使ったり、戦闘開始時の誘発を処理したりする。 | H83: アルファ (1993) | I83: 攻撃宣言の直前に割り込む機会。相手ユニットを先に凍結させるなどの防御策を差し込める。オンラインでは自動パスを既定にして待ち時間を減らす。 | J83: 中 | K83: 戦闘フェイズ | L83: × | M83: 相手ターンに割り込む仕組みが無い
A84: 83 | B84: ターン構造 | C84: 攻撃 | D84: 攻撃クリーチャー指定ステップ | E84: Declare attackers step | F84: 508 | G84: アクティブ・プレイヤーが攻撃するクリーチャーと攻撃先（プレイヤー、PW、バトル）を選ぶ。 | H84: アルファ (1993) | I84: 誰がどこを攻撃するかの選択UI。本体・召喚ユニット・攻略目標など複数の攻撃先を用意すると、ダメージの分散と集中の判断が生まれる。 | J84: 中 | K84: 攻撃・ブロック | L84: × | M84: 既存：プレイヤーかモンスターを選んで攻撃
A85: 84 | B85: ターン構造 | C85: 防御 | D85: ブロック・クリーチャー指定ステップ | E85: Declare blockers step | F85: 509 | G85: 防御側が攻撃クリーチャーをブロックするクリーチャーを選ぶ。複数で1体を止めることもできる。 | H85: アルファ (1993) | I85: StSのブロック値とは別の防御手段。ユニットで攻撃を受け止める方式を入れるなら、ブロッカーの自動割り当てを選べるようにするとオンラインの手間が減る。 | J85: 中 | K85: 攻撃・ブロック | L85: × | M85: ブロック無し（反撃・挑発で代替済み）
A86: 85 | B86: ターン構造 | C86: 攻撃 | D86: 戦闘ダメージ・ステップ | E86: Combat damage step | F86: 510 | G86: 攻撃・ブロック・クリーチャーが同時にダメージを与える。先制攻撃を持つものがいれば2回に分かれる。 | H86: アルファ (1993) | I86: 同時ダメージと先手ダメージを区別すると速攻型ユニットに価値が出る。計算は全自動にし、ログで内訳を見せるとプレイヤーの納得感が上がる。 | J86: 中 | K86: 攻撃・ブロック | L86: × | M86: 既存：攻撃と反撃は同時解決。先制攻撃はキーワード側の項目で扱う
A87: 86 | B87: ターン構造 | C87: その他 | D87: 戦闘終了ステップ | E87: End of combat step | F87: 511 | G87: 戦闘の後始末のステップ。戦闘終了時の誘発や、戦闘中だけ有効だった効果の処理を扱う。 | H87: アルファ (1993) | I87: 戦闘後に戻る・消える一時ユニットの処理タイミング。「攻撃後に手札へ戻る」効果を作るとヒット・アンド・アウェイ型の戦術が成立する。 | J87: 高 | K87: 戦闘フェイズ | L87: ◎ | M87: 【今回実装：キーワード『一撃離脱』（`hitAndRun`・バッチB）】（審査時は○）キーワード『一撃離脱』：攻撃後に手札へ戻る（召喚時効果の再利用）。±0〜+6pt
A88: 87 | B88: ターン構造 | C88: ルール基盤 | D88: 戦闘後メイン・フェイズ | E88: Postcombat main phase | F88: 505 | G88: 戦闘の後にある2回目のメイン・フェイズ。戦闘の結果を見てから呪文や土地を使える。 | H88: アルファ (1993) | I88: 攻撃結果を見てからカードを使える後半の行動枠。情報を得た後に動ける価値があるため、「戦闘後にのみ使える」制限付きカードは少し安く設計できる。 | J88: 高 | K88: 戦闘フェイズ | L88: × | M88: フェイズ分割なし（既に戦闘後にカードを使える）
A89: 88 | B89: ターン構造 | C89: 反復・再利用 | D89: 終了ステップ | E89: End step | F89: 513 | G89: ターン終了時の誘発を処理するステップ。「次の終了ステップの開始時に」という遅延効果もここで起きる。 | H89: アルファ (1993) | I89: ターン終了時効果の標準タイミング。一時的に出したユニットを終了時に消す、終了時に毒ダメージを与えるなど、遅延効果の置き場として最も使いやすい。 | J89: 高 | K89: ターン終了処理 | L89: × | M89: 既存：ターン終了時のタイミング
... A91: 90 | B91: ターン構造 | C91: その他 | D91: 追加ターン | E91: Extra turn | F91: 500.7 | G91: 現在のターンの後にもう一度自分のターンを行う効果。非常に強力なため多くは高コストか使い切り。 | H91: アルファ (1993) | I91: オンライン対戦では相手の待ち時間が延びるため、ポイントを非常に高くし、1試合1回までの制限を付けるのが安全。CPU戦専用の報酬効果にする手もある。 | J91: 中 | K91: ターン管理 | L91: △ | M91: 効果『追加ターン』レジェンド限定・1試合1回・高額(60pt+)。オンラインの待ちに注意
A92: 91 | B92: ターン構造 | C92: 攻撃 | D92: 追加の戦闘フェイズ | E92: Additional combat phase | F92: 500.8 | G92: メイン・フェイズの後にもう一度戦闘フェイズを行う効果。攻撃の回数が増える。 | I92: もう一度攻撃できる効果。ダメージ倍増に近い価値があるため、攻撃値の合計に応じてポイントを変えるか、既に行動したユニットは参加できない制限を付ける。 | J92: 中 | K92: 戦闘フェイズ | L92: ◎ | M92: 【今回実装：再行動】今回実装 効果『再行動』ready：自分のモンスター1体がもう一度攻撃できる（1体1ターン1回）
A93: 92 | B93: ゲームシステム | C93: ルール基盤 | D93: 黄金律 | E93: The Magic Golden Rules | F93: 101.1 | G93: カードの記述がルールと矛盾するときはカードが優先され、「できない」効果は「できる」効果に優先する。 | H93: アルファ (1993) | I93: 効果を自由に組めるポイント制ゲームほど必須の原則。カード文が基本ルールに勝ち、禁止効果が許可効果に勝つという優先順位をエンジンに明記すると、組み合わせの矛盾処理が一貫する。 | J93: 高 | K93: なし | L93: × | M93: ルール原則。実装方針の話でカード要素ではない
A94: 93 | B94: ゲームシステム | C94: コスト・リソース | D94: マナとマナ・プール | E94: Mana / mana pool | F94: 106 | G94: 土地などから生み出すコスト支払い用の資源。使わずに残ったマナは各ステップやフェイズの終わりに消える。 | H94: アルファ (1993) | I94: StSのエネルギーに当たる。資源カードで上限が伸びるMTG式と、毎ターン固定値で回復する方式を比べて選ぶ。ポイント制ではエネルギー1あたりの効果量を基準単位にする。 | J94: 高 | K94: マナ/エネルギー | L94: × | M94: 既存：エナジー
A95: 94 | B95: ゲームシステム | C95: コスト・リソース | D95: マナ・コスト | E95: Mana cost | F95: 202 | G95: カード右上に書かれた唱えるための費用。不特定マナと色マナの組み合わせで表される。 | H95: アルファ (1993) | I95: コストを総量と属性指定に分けると多色デッキの難しさを表現できる。属性指定が多いほど強い効果を許すポイント補正を入れると、属性の濃さに価値が出る。 | J95: 高 | K95: マナ/エネルギー | L95: × | M95: 色マナ前提
A96: 95 | B96: ゲームシステム | C96: デッキ構築 | D96: 色（5色） | E96: Color | F96: 105 | G96: 白・青・黒・赤・緑の5色。色ごとに得意な効果と苦手な効果があり、カードの個性と役割分担を決める。 | H96: アルファ (1993) | I96: 5属性ごとに得意・不得意を決め、属性ごとにポイント単価を変える（赤はダメージが安くドローが高いなど）。属性の個性が予算設計から自然に生まれる。 | J96: 高 | K96: 色・属性システム | L96: × | M96: 色前提
A97: 96 | B97: ゲームシステム | C97: デッキ構築 | D97: 多色 | E97: Multicolored | F97: 105.2b | G97: 2色以上を持つカード。両方の色のマナを要求する代わりに、各色の長所を組み合わせた強い効果を持つ。 | H97: レジェンド (1994) | I97: 2属性を組み合わせたカードは両属性のコストを要求し、その分ポイント予算を多く与える。属性の組み合わせごとに固有の効果テーマを決めるとデッキの方向性が明確になる。 | J97: 高 | K97: 色・属性システム | L97: × | M97: 色前提
A98: 97 | B98: ゲームシステム | C98: コスト・リソース | D98: 混成マナ | E98: Hybrid mana | F98: 107.4e | G98: 2色のどちらのマナでも支払える混成マナ・シンボル。片方の色だけのデッキでも使える。 | H98: ラヴニカ：ギルドの都 (2005) | I98: 赤か緑どちらのエネルギーでも払えるコスト。構築の制約が緩む代わりに、2属性の得意分野が重なる効果だけに限定してポイントを設計する。 | J98: 高 | K98: 色・属性システム | L98: × | M98: 色前提
A99: 98 | B99: ゲームシステム | C99: コスト・リソース | D99: ファイレクシア・マナ | E99: Phyrexian mana | F99: 107.4f | G99: 対応する色マナの代わりに2点のライフを支払っても払えるマナ・シンボル。 | H99: 新たなるファイレクシア (2011) | I99: エネルギーの代わりにHPで払える選択肢。どの属性のデッキでも使えてしまい問題を起こしやすいので、HPの支払い比率を高めにするか1枚制限とセットにする。 | J99: 高 | K99: HP・エネルギー | L99: △ | M99: 既存：自傷デメリットに近い。『エナジー不足時にHP払い』はコスト処理の拡張が要る
A100: 99 | B100: ゲームシステム | C100: デッキ構築 | D100: 無色 | E100: Colorless | F100: 105.2c | G100: 色を持たない状態。どの色のデッキにも入る。無色マナそのものを要求する{C}のシンボルもある。 | H100: アルファ (1993) | I100: 属性を持たない汎用カード。どの属性デッキでも使えるので、効果を属性カードより弱めにするかポイント単価を高くする。無色専用のエネルギーを要求すれば専用デッキも作れる。 | J100: 高 | K100: 色・属性システム | L100: × | M100: 色前提。全カード無色
A101: 100 | B101: ゲームシステム | C101: コスト・リソース | D101: X | E101: X | F101: 107.3 | G101: コストや効果の数値をプレイヤーが唱えるときに決める変数。多く払うほど効果も大きくなる。 | H101: アルファ (1993) | I101: 余ったエネルギーを全て注げる可変カード。終盤の使い道になる。ポイントはX=1あたりの効果量で計算し、最低保証値を付けるかどうかで単価を変える。 | J101: 高 | K101: マナ/エネルギー | L101: ◎ | M101: 【今回実装：X（全力）】今回実装 修飾『X』xEnergy：残りエナジーを全部使い、数値×使ったエナジー（#600と統合）
A102: 101 | B102: ゲームシステム | C102: ルール基盤 | D102: マナ総量 | E102: Mana value | F102: 202.3 | G102: マナ・コストに含まれるマナを色を無視して合計した値。多くの効果が条件に使う。2021年に点数で見たマナ・コストから改名された。 | H102: アルファ (1993) | I102: カードの重さを1つの数値で表し、除去や踏み倒しの条件に使う。ポイント制なら総ポイントを公開値として参照させ、「ポイント5以下を破壊」などの効果を作ると設計と効果が直結する。 | J102: 高 | K102: マナ/エネルギー | L102: ◎ | M102: 【今回実装：効果『討伐』（`slay`・バッチB）】（審査時は○）次回：効果『討伐』（コストN以下の相手モンスターを破壊。処刑のコスト版）
A103: 102 | B103: ゲームシステム | C103: ルール基盤 | D103: パワー／タフネス | E103: Power / Toughness | F103: 208 | G103: クリーチャーの攻撃力と耐久力。タフネス以上のダメージで破壊され、受けたダメージはターン終了時に消える。 | H103: アルファ (1993) | I103: ユニットの攻撃値と耐久値。MTG式に毎ターンダメージが回復するなら、耐久値は「1ターンで削り切るべき量」を意味する。ポイント換算表の基準ステータスとして使う。 | J103: 高 | K103: ユニット | L103: × | M103: 既存：攻撃力・体力
A104: 103 | B104: ゲームシステム | C104: ルール基盤 | D104: 召喚酔い | E104: Summoning sickness | F104: 302.6 | G104: 自分のターン開始時から続けてコントロールしていないクリーチャーは、攻撃もタップを含む能力の起動もできない。 | H104: アルファ (1993) | I104: 出したターンは行動できない基本制約。すぐ動ける速攻持ちとの差でポイントを付けられる。ユニットの標準ルールとして入れておくと即効性の価値が測れる。 | J104: 高 | K104: ユニット | L104: × | M104: 既存：召喚酔い・速攻
... A112: 111 | B112: ゲームシステム | C112: 防御 | D112: 置換効果・軽減効果 | E112: Replacement / Prevention effects | F112: 614 | G112: ある出来事を別の出来事に置き換える効果。「代わりに」で表され、ダメージを防ぐ軽減効果もその一種として扱う。 | H112: アルファ (1993) | I112: 「破壊される代わりに手札へ戻る」など。StSのブロック値自体が軽減効果の一種。複数かかったときの適用順を決めておかないと、多重適用で不具合が出やすい。 | J112: 低 | K112: イベントシステム | L112: × | M112: 既存：無効化・不屈・シールド
A113: 112 | B113: ゲームシステム | C113: ルール基盤 | D113: 継続効果の適用順（種類別） | E113: Interaction of continuous effects (layers) | F113: 613 | G113: 複数の継続効果が重なるとき、コピー、コントロール、タイプ、能力、P/T修整などの順に適用する仕組み。 | I113: 強化と上書きが重なるときの計算順。「基礎値の上書き→加算→倍率」の3段に単純化した順序を決めておくと、ポイント制で多様な効果が衝突しても結果が一意になる。 | J113: 中 | K113: ステータス計算 | L113: × | M113: 内部の計算順の話
A114: 113 | B114: ゲームシステム | C114: ルール基盤 | D114: 状況起因処理 | E114: State-based actions | F114: 704 | G114: ライフ0での敗北や致死ダメージを受けたクリーチャーの破壊などを、優先権が発生する前に自動で確認する処理。 | I114: HP0の撃破や同名ユニークの重複解消を毎行動後に一括でチェックする仕組み。各処理の後に必ず呼ぶ関数として実装し、チェックの順番を固定すると不具合を防げる。 | J114: 中 | K114: なし | L114: × | M114: 既存：エンジンの破壊・勝敗判定
A115: 114 | B115: ゲームシステム | C115: 勝利条件 | D115: ドローできずに敗北 | E115: Losing by drawing from an empty library | F115: 104.3c | G115: ライブラリーが空のときにカードを引こうとしたプレイヤーは、次の状況起因処理で敗北する。 | H115: アルファ (1993) | I115: 山札を削る戦術を勝ち筋にする。捨て札を山札に戻すStS型では起きないので、「山札も捨て札も尽きたら疲労ダメージ」などの罰則に置き換えて山札破壊デッキを成立させる。 | J115: 高 | K115: 山札管理 | L115: × | M115: 捨て札を切り直すので山札切れが起きない
A116: 115 | B116: ゲームシステム | C116: 勝利条件 | D116: 特殊勝利 | E116: Alternate win conditions | F116: 104.2b | G116: 「あなたはこのゲームに勝利する」という効果。条件を満たせばライフに関係なく勝てる。 | I116: 特定カード5種を揃えるなどの代替勝利条件。対戦ゲームでは対策手段も同時に用意し、達成までのターン数を見積もってポイントを高めに設定する。 | J116: 高 | K116: 条件判定 | L116: △ | M116: 特殊勝利は対策手段込みで重い。後回し
A117: 116 | B117: ゲームシステム | C117: ドロー・手札 | D117: マリガン | E117: Mulligan | F117: 103.5 | G117: 初手に不満なとき引き直せるルール。現行方式では7枚引き直した後、引き直した回数分のカードをライブラリーの下に置く。 | I117: 初手事故の救済策。「好きな枚数を山札の下に戻して引き直し、戻した数だけ手札が減る」方式が分かりやすい。CPU戦では1回無料など緩くしてよい。 | J117: 高 | K117: 初期手札 | L117: × | M117: 既存：マリガン
A118: 117 | B118: ゲームシステム | C118: ドロー・手札 | D118: 初期手札と手札の上限 | E118: Opening hand / Maximum hand size | F118: 402.2 | G118: 初手は7枚。ターン終了時に手札が8枚以上あれば、7枚になるまで捨てる。 | H118: アルファ (1993) | I118: 手札を持ち越す方式なら上限は必須。上限超過分を捨てる代わりに廃棄にするなど罰則を変えると、ドロー過多の戦略に別の意味が出る。 | J118: 高 | K118: なし | L118: × | M118: 既存：ターン終了時に手札を全部捨てる
A119: 118 | B119: ゲームシステム | C119: デッキ構築 | D119: 構築デッキのルール（60枚・4枚制限） | E119: Constructed deck rules | F119: 100.2a | G119: 構築戦のデッキは60枚以上で、基本土地以外の同名カードは4枚まで。最大15枚のサイドボードを持てる。 | I119: デッキ枚数を固定し、同名カードの上限をレアリティで変える（コモン3枚・レア1枚など）と、強いカードの重ね積みを防げる。ポイント上限との併用も可能。 | J119: 高 | K119: デッキ構築ルール | L119: × | M119: 既存：30枚・レアリティ別枚数上限
A120: 119 | B120: ゲームシステム | C120: デッキ構築 | D120: リミテッド（40枚） | E120: Limited deck rules | F120: 100.2b | G120: ドラフトやシールドなど、その場で手に入れたカードで組む形式。デッキは40枚以上で、同名カードの枚数制限はない。 | I120: オンラインのドラフト・モードとして移植しやすい。プールから順に選んで小さめのデッキを組む形式は、ポイント制カードの強さ検証にも役立つ。 | J120: 中 | K120: ドラフトUI | L120: △ | M120: ドラフトモードは将来候補。カード要素ではない
A121: 120 | B121: ゲームシステム | C121: デッキ構築 | D121: 統率者戦（コマンダー）のデッキ構築 | E121: Commander deck construction | F121: 903.5 | G121: 統率者を含むちょうど100枚で、基本土地以外は同名1枚まで。初期ライフは40点。日本語名は2026年にコマンダーへ変更。 | H121: 統率者 (2011) | I121: 全カード1枚制限の大型デッキ形式。ランダム性が高く毎回展開が変わる。ポイント制なら「1枚制限の代わりにポイント上限を緩める」別モードとして用意できる。 | J121: 高 | K121: デッキ構築ルール | L121: × | M121: 統率者前提
A122: 121 | B122: ゲームシステム | C122: デッキ構築 | D122: 固有色 | E122: Color identity | F122: 903.4 | G122: 統率者のマナ・コストや文章中のマナ・シンボルで決まる色。デッキのカードはその色の範囲に限られる。 | H122: 統率者 (2011) | I122: リーダーの属性がデッキに入れられるカードを決める仕組み。リーダー選びが構築の制約になるので、リーダーごとに使える属性を2つまでにするとキャラの個性が出る。 | J122: 高 | K122: キャラ選択 | L122: × | M122: 色前提
A123: 122 | B123: ゲームシステム | C123: デッキ構築 | D123: レアリティ | E123: Rarity | F123: 206.2 | G123: コモン・アンコモン・レア・神話レアの4段階。エキスパンション・シンボルの色で示され、封入率が異なる。 | H123: アルファ (1993) | I123: ユーザーのゲームにもある概念。レアリティごとにポイント予算の上限を変える（コモン10点・レア15点など）と、レアリティが強さと直結して調整しやすい。 | J123: 高 | K123: デッキ構築ルール | L123: × | M123: 既存：レアリティ
A124: 123 | B124: ゲームシステム | C124: ルール基盤 | D124: レジェンド・ルール | E124: Legend rule | F124: 704.5j | G124: 同じプレイヤーが同名の伝説のパーマネントを2つ以上持つと、1つを選んで残りを墓地に置く。 | H124: レジェンド (1994) | I124: 同名ユニークの重複を自動で解消する処理。重複時に古い方と新しい方のどちらを残すか選ばせると、登場時効果を再利用するテクニックが生まれる。 | J124: 高 | K124: ユニーク判定 | L124: × | M124: No.17の『伝説』デメリットに統合
A125: 124 | B125: ゲームシステム | C125: 展開・トークン | D125: トークン | E125: Token | F125: 111 | G125: カードではなく効果によって生成されるパーマネント。戦場から他の領域へ移ると消滅する。 | H125: アルファ (1993) | I125: 一時ユニットや一時カードの生成。「捨て札に行くと消える」処理はデジタルなら簡単。生成数×1体の価値でポイント化し、定義済みトークンを少数用意するとカード文が短くなる。 | J125: 高 | K125: ユニット | L125: ◎ | M125: 【今回実装：トークン生成】今回実装 効果『トークン生成』token：攻撃力・体力Nの小鬼をM体（#604と統合）
A126: 125 | B126: ゲームシステム | C126: 反復・再利用 | D126: コピー | E126: Copy | F126: 707 | G126: 他のオブジェクトの写しとなる値を取り込む効果。呪文のコピーやコピーのトークンを作れる。 | H126: アルファ (1993) | I126: 手札や場のカードを複製する効果。データの複製は簡単だが、コピーにさらにコピー効果が重なると暴走するので、複製元のポイントに応じてコストが増える設計にする。 | J126: 高 | K126: なし | L126: × | M126: 既存：複製
A127: 126 | B127: ゲームシステム | C127: ルール基盤 | D127: ダメージとライフの喪失 | E127: Damage vs. life loss | F127: 120.3 | G127: ダメージは軽減や絆魂などの対象になるが、ライフの喪失は発生源を持たず軽減できない。 | H127: アルファ (1993) | I127: StS型でいえば「ブロック値で防げる攻撃」と「ブロックを貫通するHP減少」の違い。両者を明確に分け、貫通側のポイント単価を高く設定すると防御デッキへの対策になる。 | J127: 高 | K127: HP・ブロック値 | L127: × | M127: 既存：防御無視（守備力・シールドを無視）
A128: 127 | B128: ゲームシステム | C128: 妨害 | D128: オーナーとコントローラー | E128: Owner / Controller | F128: 108.3 | G128: カードの持ち主と、現在それを操作しているプレイヤーの区別。コントロール奪取の効果で両者が分かれる。 | H128: アルファ (1993) | I128: 相手のユニットを一時的に奪う効果の基盤。所有者IDと操作者IDを分けて持たせ、効果終了時やカードが場を離れたときに所有者へ戻す処理を共通化する。 | J128: 中 | K128: ユニット | L128: ◎ | M128: 【今回実装：効果『借用』（`borrow`・バッチB）】（審査時は○）効果『一時奪取』：相手モンスター1体をこのターンだけ奪い速攻を与え、ターン終了時に返す。レア以上
A129: 128 | B129: ゲームシステム | C129: ルール基盤 | D129: 対象 | E129: Target | F129: 115 | G129: 呪文や能力が影響を与える相手を唱えるときに選ぶ仕組み。解決時に対象が不正だと効果は起きない。 | H129: アルファ (1993) | I129: 対象を取る効果と取らない全体効果を区別すると、「対象にならない」耐性を作れる。選択UIはクリックだけで済むが、不正対象のチェックを共通化しておく。 | J129: 中 | K129: なし | L129: ◎ | M129: 【今回実装：呪禁】今回実装 キーワード『呪禁』hexproof（#206と統合）
A130: 129 | B130: ゲームシステム | C130: コスト・リソース | D130: 土地のプレイ（1ターン1回） | E130: Playing a land | F130: 305.2 | G130: 土地は唱えずにプレイする特別な処理。通常は自分のメイン・フェイズに1ターン1回だけ行える。 | H130: アルファ (1993) | I130: 資源カードを置ける回数を1ターン1回に制限する。追加で資源を置ける効果に価値が出る。資源はコストなしで置ける代わりに、回数の枠で調整する。 | J130: 高 | K130: 資源カード | L130: × | M130: 土地前提
A131: 130 | B131: ゲームシステム | C131: 成長・カウンター | D131: 両面カード | E131: Double-faced cards | F131: 712 | G131: 表と裏の2つの面を持つカード。変身で裏返り、別の特性を持つカードとして働く。 | H131: イニストラード (2011) | I131: 条件達成で裏面に変わる成長カード。デジタルなら物理的な裏面は不要で演出も付けられる。表と裏のポイントを別々に計算し、変身条件の難しさで裏面を割り引く。 | J131: 中 | K131: 状態フラグ | L131: × | M131: No.56の進化に統合
A132: 131 | B132: ゲームシステム | C132: その他 | D132: サイコロとコイン投げ | E132: Rolling a die / Flipping a coin | F132: 706 | G132: ダイスを振る、コインを投げるなど乱数を使う効果。出目や表裏によって結果が変わる。 | I132: 乱数を見せる演出。デジタルでは偏りを抑えた疑似乱数も選べる。期待値でポイントを算出し、振り直し効果をセットにすると運要素をプレイヤーが制御できる。 | J132: 高 | K132: 乱数 | L132: ◎ | M132: 【今回実装：コイン投げで表（50%）】今回実装 条件『コイン投げで表（50%）』coinFlip（シード付き乱数）
A133: 132 | B133: ゲームシステム | C133: 強化 | D133: ステッカー | E133: Stickers | F133: 123 | G133: Unfinityの仕組み。チケット・カウンターを払って名前・能力・P/Tのステッカーをカードに貼り、恒久的に書き換える。 | H133: Unfinity (2022) | I133: デジタル向きのカード書き換え。試合中に得た強化パーツをカードに貼る仕組みは、ポイント制のカスタム要素と直結する。貼れる枚数上限で強さを調整する。 | J133: 中 | K133: カード書き換え | L133: × | M133: カード書き換えは重い
...

Sheet 集計
A1: 大分類 × 導入しやすさ
A3: 大分類 | B3: 件数 | C3: 導入しやすさ 高 | D3: 中 | E3: 低 | F3: 採用検討 ◎ | G3: ○ | H3: △ | I3: × | J3: 未検討
A4: カードタイプ | B4: =COUNTIF(全要素一覧!$B$2:$B$642,A4) | C4: =COUNTIFS(全要素一覧!$B$2:$B$642,$A4,全要素一覧!$J$2:$J$642,"高") | D4: =COUNTIFS(全要素一覧!$B$2:$B$642,$A4,全要素一覧!$J$2:$J$642,"中") | E4: =COUNTIFS(全要素一覧!$B$2:$B$642,$A4,全要素一覧!$J$2:$J$642,"低") | F4: =COUNTIFS(全要素一覧!$B$2:$B$642,$A4,全要素一覧!$L$2:$L$642,"◎") | G4: =COUNTIFS(全要素一覧!$B$2:$B$642,$A4,全要素一覧!$L$2:$L$642,"○") | H4: =COUNTIFS(全要素一覧!$B$2:$B$642,$A4,全要素一覧!$L$2:$L$642,"△") | I4: =COUNTIFS(全要素一覧!$B$2:$B$642,$A4,全要素一覧!$L$2:$L$642,"×") | J4: =B4-SUM(F4:I4)
A5: 特殊タイプ | B5: =COUNTIF(全要素一覧!$B$2:$B$642,A5) | C5: =COUNTIFS(全要素一覧!$B$2:$B$642,$A5,全要素一覧!$J$2:$J$642,"高") | D5: =COUNTIFS(全要素一覧!$B$2:$B$642,$A5,全要素一覧!$J$2:$J$642,"中") | E5: =COUNTIFS(全要素一覧!$B$2:$B$642,$A5,全要素一覧!$J$2:$J$642,"低") | F5: =COUNTIFS(全要素一覧!$B$2:$B$642,$A5,全要素一覧!$L$2:$L$642,"◎") | G5: =COUNTIFS(全要素一覧!$B$2:$B$642,$A5,全要素一覧!$L$2:$L$642,"○") | H5: =COUNTIFS(全要素一覧!$B$2:$B$642,$A5,全要素一覧!$L$2:$L$642,"△") | I5: =COUNTIFS(全要素一覧!$B$2:$B$642,$A5,全要素一覧!$L$2:$L$642,"×") | J5: =B5-SUM(F5:I5)
A6: サブタイプ | B6: =COUNTIF(全要素一覧!$B$2:$B$642,A6) | C6: =COUNTIFS(全要素一覧!$B$2:$B$642,$A6,全要素一覧!$J$2:$J$642,"高") | D6: =COUNTIFS(全要素一覧!$B$2:$B$642,$A6,全要素一覧!$J$2:$J$642,"中") | E6: =COUNTIFS(全要素一覧!$B$2:$B$642,$A6,全要素一覧!$J$2:$J$642,"低") | F6: =COUNTIFS(全要素一覧!$B$2:$B$642,$A6,全要素一覧!$L$2:$L$642,"◎") | G6: =COUNTIFS(全要素一覧!$B$2:$B$642,$A6,全要素一覧!$L$2:$L$642,"○") | H6: =COUNTIFS(全要素一覧!$B$2:$B$642,$A6,全要素一覧!$L$2:$L$642,"△") | I6: =COUNTIFS(全要素一覧!$B$2:$B$642,$A6,全要素一覧!$L$2:$L$642,"×") | J6: =B6-SUM(F6:I6)
A7: カードレイアウト | B7: =COUNTIF(全要素一覧!$B$2:$B$642,A7) | C7: =COUNTIFS(全要素一覧!$B$2:$B$642,$A7,全要素一覧!$J$2:$J$642,"高") | D7: =COUNTIFS(全要素一覧!$B$2:$B$642,$A7,全要素一覧!$J$2:$J$642,"中") | E7: =COUNTIFS(全要素一覧!$B$2:$B$642,$A7,全要素一覧!$J$2:$J$642,"低") | F7: =COUNTIFS(全要素一覧!$B$2:$B$642,$A7,全要素一覧!$L$2:$L$642,"◎") | G7: =COUNTIFS(全要素一覧!$B$2:$B$642,$A7,全要素一覧!$L$2:$L$642,"○") | H7: =COUNTIFS(全要素一覧!$B$2:$B$642,$A7,全要素一覧!$L$2:$L$642,"△") | I7: =COUNTIFS(全要素一覧!$B$2:$B$642,$A7,全要素一覧!$L$2:$L$642,"×") | J7: =B7-SUM(F7:I7)
A8: ゾーン | B8: =COUNTIF(全要素一覧!$B$2:$B$642,A8) | C8: =COUNTIFS(全要素一覧!$B$2:$B$642,$A8,全要素一覧!$J$2:$J$642,"高") | D8: =COUNTIFS(全要素一覧!$B$2:$B$642,$A8,全要素一覧!$J$2:$J$642,"中") | E8: =COUNTIFS(全要素一覧!$B$2:$B$642,$A8,全要素一覧!$J$2:$J$642,"低") | F8: =COUNTIFS(全要素一覧!$B$2:$B$642,$A8,全要素一覧!$L$2:$L$642,"◎") | G8: =COUNTIFS(全要素一覧!$B$2:$B$642,$A8,全要素一覧!$L$2:$L$642,"○") | H8: =COUNTIFS(全要素一覧!$B$2:$B$642,$A8,全要素一覧!$L$2:$L$642,"△") | I8: =COUNTIFS(全要素一覧!$B$2:$B$642,$A8,全要素一覧!$L$2:$L$642,"×") | J8: =B8-SUM(F8:I8)
A9: ターン構造 | B9: =COUNTIF(全要素一覧!$B$2:$B$642,A9) | C9: =COUNTIFS(全要素一覧!$B$2:$B$642,$A9,全要素一覧!$J$2:$J$642,"高") | D9: =COUNTIFS(全要素一覧!$B$2:$B$642,$A9,全要素一覧!$J$2:$J$642,"中") | E9: =COUNTIFS(全要素一覧!$B$2:$B$642,$A9,全要素一覧!$J$2:$J$642,"低") | F9: =COUNTIFS(全要素一覧!$B$2:$B$642,$A9,全要素一覧!$L$2:$L$642,"◎") | G9: =COUNTIFS(全要素一覧!$B$2:$B$642,$A9,全要素一覧!$L$2:$L$642,"○") | H9: =COUNTIFS(全要素一覧!$B$2:$B$642,$A9,全要素一覧!$L$2:$L$642,"△") | I9: =COUNTIFS(全要素一覧!$B$2:$B$642,$A9,全要素一覧!$L$2:$L$642,"×") | J9: =B9-SUM(F9:I9)
A10: ゲームシステム | B10: =COUNTIF(全要素一覧!$B$2:$B$642,A10) | C10: =COUNTIFS(全要素一覧!$B$2:$B$642,$A10,全要素一覧!$J$2:$J$642,"高") | D10: =COUNTIFS(全要素一覧!$B$2:$B$642,$A10,全要素一覧!$J$2:$J$642,"中") | E10: =COUNTIFS(全要素一覧!$B$2:$B$642,$A10,全要素一覧!$J$2:$J$642,"低") | F10: =COUNTIFS(全要素一覧!$B$2:$B$642,$A10,全要素一覧!$L$2:$L$642,"◎") | G10: =COUNTIFS(全要素一覧!$B$2:$B$642,$A10,全要素一覧!$L$2:$L$642,"○") | H10: =COUNTIFS(全要素一覧!$B$2:$B$642,$A10,全要素一覧!$L$2:$L$642,"△") | I10: =COUNTIFS(全要素一覧!$B$2:$B$642,$A10,全要素一覧!$L$2:$L$642,"×") | J10: =B10-SUM(F10:I10)
A11: カウンター | B11: =COUNTIF(全要素一覧!$B$2:$B$642,A11) | C11: =COUNTIFS(全要素一覧!$B$2:$B$642,$A11,全要素一覧!$J$2:$J$642,"高") | D11: =COUNTIFS(全要素一覧!$B$2:$B$642,$A11,全要素一覧!$J$2:$J$642,"中") | E11: =COUNTIFS(全要素一覧!$B$2:$B$642,$A11,全要素一覧!$J$2:$J$642,"低") | F11: =COUNTIFS(全要素一覧!$B$2:$B$642,$A11,全要素一覧!$L$2:$L$642,"◎") | G11: =COUNTIFS(全要素一覧!$B$2:$B$642,$A11,全要素一覧!$L$2:$L$642,"○") | H11: =COUNTIFS(全要素一覧!$B$2:$B$642,$A11,全要素一覧!$L$2:$L$642,"△") | I11: =COUNTIFS(全要素一覧!$B$2:$B$642,$A11,全要素一覧!$L$2:$L$642,"×") | J11: =B11-SUM(F11:I11)
A12: トークン | B12: =COUNTIF(全要素一覧!$B$2:$B$642,A12) | C12: =COUNTIFS(全要素一覧!$B$2:$B$642,$A12,全要素一覧!$J$2:$J$642,"高") | D12: =COUNTIFS(全要素一覧!$B$2:$B$642,$A12,全要素一覧!$J$2:$J$642,"中") | E12: =COUNTIFS(全要素一覧!$B$2:$B$642,$A12,全要素一覧!$J$2:$J$642,"低") | F12: =COUNTIFS(全要素一覧!$B$2:$B$642,$A12,全要素一覧!$L$2:$L$642,"◎") | G12: =COUNTIFS(全要素一覧!$B$2:$B$642,$A12,全要素一覧!$L$2:$L$642,"○") | H12: =COUNTIFS(全要素一覧!$B$2:$B$642,$A12,全要素一覧!$L$2:$L$642,"△") | I12: =COUNTIFS(全要素一覧!$B$2:$B$642,$A12,全要素一覧!$L$2:$L$642,"×") | J12: =B12-SUM(F12:I12)
A13: 指定・状態 | B13: =COUNTIF(全要素一覧!$B$2:$B$642,A13) | C13: =COUNTIFS(全要素一覧!$B$2:$B$642,$A13,全要素一覧!$J$2:$J$642,"高") | D13: =COUNTIFS(全要素一覧!$B$2:$B$642,$A13,全要素一覧!$J$2:$J$642,"中") | E13: =COUNTIFS(全要素一覧!$B$2:$B$642,$A13,全要素一覧!$J$2:$J$642,"低") | F13: =COUNTIFS(全要素一覧!$B$2:$B$642,$A13,全要素一覧!$L$2:$L$642,"◎") | G13: =COUNTIFS(全要素一覧!$B$2:$B$642,$A13,全要素一覧!$L$2:$L$642,"○") | H13: =COUNTIFS(全要素一覧!$B$2:$B$642,$A13,全要素一覧!$L$2:$L$642,"△") | I13: =COUNTIFS(全要素一覧!$B$2:$B$642,$A13,全要素一覧!$L$2:$L$642,"×") | J13: =B13-SUM(F13:I13)
A14: キーワード能力 | B14: =COUNTIF(全要素一覧!$B$2:$B$642,A14) | C14: =COUNTIFS(全要素一覧!$B$2:$B$642,$A14,全要素一覧!$J$2:$J$642,"高") | D14: =COUNTIFS(全要素一覧!$B$2:$B$642,$A14,全要素一覧!$J$2:$J$642,"中") | E14: =COUNTIFS(全要素一覧!$B$2:$B$642,$A14,全要素一覧!$J$2:$J$642,"低") | F14: =COUNTIFS(全要素一覧!$B$2:$B$642,$A14,全要素一覧!$L$2:$L$642,"◎") | G14: =COUNTIFS(全要素一覧!$B$2:$B$642,$A14,全要素一覧!$L$2:$L$642,"○") | H14: =COUNTIFS(全要素一覧!$B$2:$B$642,$A14,全要素一覧!$L$2:$L$642,"△") | I14: =COUNTIFS(全要素一覧!$B$2:$B$642,$A14,全要素一覧!$L$2:$L$642,"×") | J14: =B14-SUM(F14:I14)
A15: キーワード処理 | B15: =COUNTIF(全要素一覧!$B$2:$B$642,A15) | C15: =COUNTIFS(全要素一覧!$B$2:$B$642,$A15,全要素一覧!$J$2:$J$642,"高") | D15: =COUNTIFS(全要素一覧!$B$2:$B$642,$A15,全要素一覧!$J$2:$J$642,"中") | E15: =COUNTIFS(全要素一覧!$B$2:$B$642,$A15,全要素一覧!$J$2:$J$642,"低") | F15: =COUNTIFS(全要素一覧!$B$2:$B$642,$A15,全要素一覧!$L$2:$L$642,"◎") | G15: =COUNTIFS(全要素一覧!$B$2:$B$642,$A15,全要素一覧!$L$2:$L$642,"○") | H15: =COUNTIFS(全要素一覧!$B$2:$B$642,$A15,全要素一覧!$L$2:$L$642,"△") | I15: =COUNTIFS(全要素一覧!$B$2:$B$642,$A15,全要素一覧!$L$2:$L$642,"×") | J15: =B15-SUM(F15:I15)
... A19: デザイン手法 | B19: =COUNTIF(全要素一覧!$B$2:$B$642,A19) | C19: =COUNTIFS(全要素一覧!$B$2:$B$642,$A19,全要素一覧!$J$2:$J$642,"高") | D19: =COUNTIFS(全要素一覧!$B$2:$B$642,$A19,全要素一覧!$J$2:$J$642,"中") | E19: =COUNTIFS(全要素一覧!$B$2:$B$642,$A19,全要素一覧!$J$2:$J$642,"低") | F19: =COUNTIFS(全要素一覧!$B$2:$B$642,$A19,全要素一覧!$L$2:$L$642,"◎") | G19: =COUNTIFS(全要素一覧!$B$2:$B$642,$A19,全要素一覧!$L$2:$L$642,"○") | H19: =COUNTIFS(全要素一覧!$B$2:$B$642,$A19,全要素一覧!$L$2:$L$642,"△") | I19: =COUNTIFS(全要素一覧!$B$2:$B$642,$A19,全要素一覧!$L$2:$L$642,"×") | J19: =B19-SUM(F19:I19)
A20: 合計 | B20: =SUM(B4:B19) | C20: =SUM(C4:C19) | D20: =SUM(D4:D19) | E20: =SUM(E4:E19) | F20: =SUM(F4:F19) | G20: =SUM(G4:G19) | H20: =SUM(H4:H19) | I20: =SUM(I4:I19) | J20: =SUM(J4:J19)
A22: 機能タグ別の件数
A23: 機能タグ | B23: 件数 | C23: うち導入しやすさ 高
A24: 攻撃 | B24: =COUNTIF(全要素一覧!$C$2:$C$642,A24) | C24: =COUNTIFS(全要素一覧!$C$2:$C$642,A24,全要素一覧!$J$2:$J$642,"高")
A25: 回避 | B25: =COUNTIF(全要素一覧!$C$2:$C$642,A25) | C25: =COUNTIFS(全要素一覧!$C$2:$C$642,A25,全要素一覧!$J$2:$J$642,"高")
A26: 防御 | B26: =COUNTIF(全要素一覧!$C$2:$C$642,A26) | C26: =COUNTIFS(全要素一覧!$C$2:$C$642,A26,全要素一覧!$J$2:$J$642,"高")
A27: 除去 | B27: =COUNTIF(全要素一覧!$C$2:$C$642,A27) | C27: =COUNTIFS(全要素一覧!$C$2:$C$642,A27,全要素一覧!$J$2:$J$642,"高")
A28: 妨害 | B28: =COUNTIF(全要素一覧!$C$2:$C$642,A28) | C28: =COUNTIFS(全要素一覧!$C$2:$C$642,A28,全要素一覧!$J$2:$J$642,"高")
A29: ドロー・手札 | B29: =COUNTIF(全要素一覧!$C$2:$C$642,A29) | C29: =COUNTIFS(全要素一覧!$C$2:$C$642,A29,全要素一覧!$J$2:$J$642,"高")
A30: 山札操作 | B30: =COUNTIF(全要素一覧!$C$2:$C$642,A30) | C30: =COUNTIFS(全要素一覧!$C$2:$C$642,A30,全要素一覧!$J$2:$J$642,"高")
A31: 墓地利用 | B31: =COUNTIF(全要素一覧!$C$2:$C$642,A31) | C31: =COUNTIFS(全要素一覧!$C$2:$C$642,A31,全要素一覧!$J$2:$J$642,"高")
A32: コスト・リソース | B32: =COUNTIF(全要素一覧!$C$2:$C$642,A32) | C32: =COUNTIFS(全要素一覧!$C$2:$C$642,A32,全要素一覧!$J$2:$J$642,"高")
A33: 展開・トークン | B33: =COUNTIF(全要素一覧!$C$2:$C$642,A33) | C33: =COUNTIFS(全要素一覧!$C$2:$C$642,A33,全要素一覧!$J$2:$J$642,"高")
A34: 強化 | B34: =COUNTIF(全要素一覧!$C$2:$C$642,A34) | C34: =COUNTIFS(全要素一覧!$C$2:$C$642,A34,全要素一覧!$J$2:$J$642,"高")
A35: 成長・カウンター | B35: =COUNTIF(全要素一覧!$C$2:$C$642,A35) | C35: =COUNTIFS(全要素一覧!$C$2:$C$642,A35,全要素一覧!$J$2:$J$642,"高")
... A42: その他 | B42: =COUNTIF(全要素一覧!$C$2:$C$642,A42) | C42: =COUNTIFS(全要素一覧!$C$2:$C$642,A42,全要素一覧!$J$2:$J$642,"高")
